setup.py
chain/__init__.py
chain/lib.py
chain/shared.py
chain_sdk.egg-info/PKG-INFO
chain_sdk.egg-info/SOURCES.txt
chain_sdk.egg-info/dependency_links.txt
chain_sdk.egg-info/requires.txt
chain_sdk.egg-info/top_level.txt