Metadata-Version: 1.1
Name: chain-sdk
Version: 1.0
Summary: Official Python software development kit for the Chain.com API
Home-page: https://github.com/chain-engineering/chain-python
Author: Jonathan Warren
Author-email: jonathan@coinapex.com
License: LICENSE
Keywords: bitcoin
Platform: UNKNOWN
Classifier: Programming Language :: Python :: 2
Classifier: Programming Language :: Python :: 2.7
Classifier: Programming Language :: Python :: 3
Classifier: Programming Language :: Python :: 3.4
Classifier: Intended Audience :: Developers
Classifier: Natural Language :: English
Classifier: License :: OSI Approved :: MIT License
